Workbook

Sheet Hp
A1: FONDOS HP
A3: 1. INGRESO DE FONDOS
A4: Periodo | B4: USD | C4: TRM | D4: COP | E4: Observación
A5: 26Q1 | B5: 2200 | C5: 3500 | D5: =B5*C5 -> 7700000
A6: 26Q1 | B6: 1000 | C6: 3500 | D6: =B6*C6 -> 3500000
A7: 26Q1 | B7: 1500 | C7: 3500 | D7: =B7*C7 -> 5250000
A8: 26Q1 | B8: 1500 | C8: 3500 | D8: =B8*C8 -> 5250000
A9: 26Q2 | B9: 3000 | C9: 3500 | D9: =B9*C9 -> 10500000
A10: 26Q2 | B10: 3000 | C10: 3500 | D10: =B10*C10 -> 10500000
A11: 26Q2 | B11: 1000 | C11: 3500 | D11: =B11*C11 -> 3500000
A12: 26Q3 | B12: 3000 | C12: 3500 | D12: =B12*C12 -> 10500000
A13: 26Q3 | B13: 1000 | C13: 3500 | D13: =B13*C13 -> 3500000
A14: Total ingreso | B14: =SUM(B5:B13) -> 17200 | D14: =SUM(D5:D13) -> 60200000
A16: 2. SALIDAS (EJECUCIÓN)
A17: Tipo | B17: Concepto | C17: Fecha / Cupos | D17: COP | E17: Observación
A18: Evento | B18: HP Suministros - Evento | D18: 2710400
A19: Evento | B19: Liga Z - Capacitación | D19: 486000
A20: Evento | B20: HP Workstation - Hotel Hilton | D20: 1322585
A21: Evento | B21: HP Nueva era de la tecnología - Hotel | D21: 5943183
A22: Incentivo | B22: Concurso Supplies | D22: 2500000
A23: Incentivo | B23: Concurso venta portafolio HP | D23: 3000000
A24: Incentivo | B24: Campaña Suministros | D24: 6000000
A25: Incentivo | B25: Camisetas (obsequio gerencia comercial y direcciones) | D25: 1500000
A26: Incentivo | B26: Incentivo Suministros (ganadora Dilma - bono Adidas) | D26: 300000
A27: Incentivo | B27: Nintendo | D27: 2600000
A28: Rio | B28: Rio (20 al 24 mayo) - cupos @ $6.500.000 | C28: 3 | D28: =C28*6500000 -> 19500000
A29: Total salida | D29: =SUM(D18:D28) -> 45862168
A31: 3. RESUMEN
A32: Total ingreso (COP) | D32: =D14 -> 60200000
A33: Salidas - Eventos | D33: =SUMIF($A$18:$A$28,"Evento",$D$18:$D$28) -> 10462168
A34: Salidas - Incentivos | D34: =SUMIF($A$18:$A$28,"Incentivo",$D$18:$D$28) -> 15900000
A35: Salidas - Rio | D35: =SUMIF($A$18:$A$28,"Rio",$D$18:$D$28) -> 19500000
A36: Total salida (COP) | D36: =D29 -> 45862168
A37: SALDO (COP) | D37: =D32-D36 -> 14337832
A38: Comisión Dir. Mercadeo (10%) | D38: =D37*10% -> 1433783.2
A40: Notas: TRM estándar 3.500. En la versión anterior los encabezados de evento/incentivo estaban corridos una columna respecto a sus montos; aquí cada monto queda junto a su concepto.

Sheet Dell
A1: FONDOS DELL
A3: 1. INGRESO DE FONDOS
A4: Periodo | B4: USD | C4: TRM | D4: COP | E4: Vigencia / Observación
A5: 2026 Q3 | B5: 1414.49 | C5: 3500 | D5: =B5*C5 -> 4950715 | E5: Agosto - Octubre
A6: 2026 Q4 | B6: 967 | C6: 3500 | D6: =B6*C6 -> 3384500 | E6: Noviembre 1 - Enero 30 (revisar: debería cerrar en enero 2027)
A7: 2027 Q1 | B7: 2864 | C7: 3500 | D7: =B7*C7 -> 10024000 | E7: Enero 31 - Mayo 1
A8: 2027 Q2 | B8: 1811 | C8: 3500 | D8: =B8*C8 -> 6338500 | E8: Mayo 2 - Julio 31
A9: Subtotal plataformas | B9: =SUM(B5:B8) -> 7056.49 | D9: =SUM(D5:D8) -> 24697715
A10: Fondos Proposal | B10: 9500 | C10: 3500 | D10: =B10*C10 -> 33250000 | E10: Generación de demanda; se factura a nombre de Dell
A11: Total ingreso | B11: =B9+B10 -> 16556.49 | D11: =D9+D10 -> 57947715
A13: 2. SALIDAS (EJECUCIÓN)
A14: Tipo | B14: Concepto | C14: Fecha / Cupos | D14: COP | E14: Observación
A15: Evento | B15: Infraestructura | C15: 24 de abril 2026 | D15: 8874800
A16: Evento | B16: Tecnología cómputo | C16: 17 de julio 2026 | D16: 6452650
A17: Incentivo | B17: Televisor, Apple TV, bonos H&M | D17: 3000000
A18: Incentivo | B18: Play Station | D18: 2600000
A19: Rio | B19: Rio (20 al 24 mayo) - cupos @ $6.500.000 | C19: 2 | D19: =C19*6500000 -> 13000000
A20: Total salida | D20: =SUM(D15:D19) -> 33927450
A22: 3. RESUMEN
A23: Total ingreso (COP) | D23: =D11 -> 57947715
A24: Salidas - Eventos | D24: =SUMIF($A$15:$A$19,"Evento",$D$15:$D$19) -> 15327450
A25: Salidas - Incentivos | D25: =SUMIF($A$15:$A$19,"Incentivo",$D$15:$D$19) -> 5600000
A26: Salidas - Rio | D26: =SUMIF($A$15:$A$19,"Rio",$D$15:$D$19) -> 13000000
A27: Total salida (COP) | D27: =D20 -> 33927450
A28: SALDO (COP) | D28: =D23-D27 -> 24020265
A29: Comisión Dir. Mercadeo (10%) | D29: =D28*10% -> 2402026.5
A31: Notas: el ingreso incluye 'Fondos Proposal' (USD 9.500) que aún no se ejecuta; si se excluye, el saldo disponible real baja en $33.250.000.

Sheet Lenovo
A1: FONDOS LENOVO
A3: 1. INGRESO DE FONDOS
A4: Periodo | B4: USD | C4: TRM | D4: COP | E4: Estado
A5: Q2 | B5: 1906 | C5: 3500 | D5: =B5*C5 -> 6671000 | E5: Confirmado
A6: Q3 | B6: 2997 | C6: 3500 | D6: =B6*C6 -> 10489500 | E6: Confirmado
A7: Q4 | B7: 3349 | C7: 3500 | D7: =B7*C7 -> 11721500 | E7: Sin factura de Provexpress - pendiente por ejecutar
A8: Total confirmado | B8: =SUMIF($E$5:$E$7,"Confirmado",$B$5:$B$7) -> 4903 | D8: =SUMIF($E$5:$E$7,"Confirmado",$D$5:$D$7) -> 17160500
A9: Total con Q4 pendiente | B9: =SUM(B5:B7) -> 8252 | D9: =SUM(D5:D7) -> 28882000
A11: 2. SALIDAS (EJECUCIÓN)
A12: Tipo | B12: Concepto | C12: Fecha / Cupos | D12: COP | E12: Observación
A13: Evento | B13: Infraestructura | D13: 4408950
A14: Incentivo | B14: Lenovo Legion Go S | D14: 2500000
A15: Incentivo | B15: Bono María Paola Briceño | D15: 500000
A16: Rio | B16: Rio (20 al 24 mayo) - cupos @ $6.500.000 | C16: 1.5 | D16: =C16*6500000 -> 9750000
A17: Total salida | D17: =SUM(D13:D16) -> 17158950
A19: 3. RESUMEN
A20: Total ingreso confirmado (COP) | D20: =D8 -> 17160500
A21: Salidas - Eventos | D21: =SUMIF($A$13:$A$16,"Evento",$D$13:$D$16) -> 4408950
A22: Salidas - Incentivos | D22: =SUMIF($A$13:$A$16,"Incentivo",$D$13:$D$16) -> 3000000
A23: Salidas - Rio | D23: =SUMIF($A$13:$A$16,"Rio",$D$13:$D$16) -> 9750000
A24: Total salida (COP) | D24: =D17 -> 17158950
A25: SALDO (COP) | D25: =D20-D24 -> 1550
A26: Comisión Dir. Mercadeo (10%) | D26: =D25*10% -> 155
A28: Notas: el Q4 (USD 3.349 = $11.721.500) NO entra al total confirmado porque no tiene factura de Provexpress. El encabezado original decía '1,5 cupos' y el cálculo coincide.

Sheet Intel
A1: FONDOS INTEL
A3: 1. INGRESO DE FONDOS
A4: Periodo | B4: USD | C4: TRM | D4: COP | E4: Observación
A5: H1 | B5: 4990 | C5: 3500 | D5: =B5*C5 -> 17465000
A6: Total ingreso | B6: =SUM(B5:B5) -> 4990 | D6: =SUM(D5:D5) -> 17465000
A8: 2. SALIDAS (EJECUCIÓN)
A9: Tipo | B9: Concepto | C9: Fecha / Cupos | D9: COP | E9: Observación
A10: Evento | B10: Evento (USD 490) | D10: 1715000
A11: Incentivo | B11: Capacitación Rosario - código de vestimenta | D11: 6000000
A12: Rio | B12: Rio (20 al 24 mayo) - cupos @ $6.500.000 | C12: 1.5 | D12: =C12*6500000 -> 9750000 | E12: Encabezado original decía 2 cupos
A13: Total salida | D13: =SUM(D10:D12) -> 17465000
A15: 3. RESUMEN
A16: Total ingreso (COP) | D16: =D6 -> 17465000
A17: Salidas - Eventos | D17: =SUMIF($A$10:$A$12,"Evento",$D$10:$D$12) -> 1715000
A18: Salidas - Incentivos | D18: =SUMIF($A$10:$A$12,"Incentivo",$D$10:$D$12) -> 6000000
A19: Salidas - Rio | D19: =SUMIF($A$10:$A$12,"Rio",$D$10:$D$12) -> 9750000
A20: Total salida (COP) | D20: =D13 -> 17465000
A21: SALDO (COP) | D21: =D16-D20 -> 0
A22: Comisión Dir. Mercadeo (10%) | D22: =D21*10% -> 0
A24: Notas: el encabezado original decía '2 cupos' de Rio pero el cálculo usaba 1,5. Se dejó 1,5 (celda C12 editable) para no alterar el saldo; si son 2 cupos, cambie C12 y el saldo pasará a -$3.250.000.

Sheet Microsoft
A1: FONDOS MICROSOFT
A3: 1. INGRESO DE FONDOS
A4: Origen | B4: USD | C4: TRM | D4: COP | E4: Observación
A5: LOL | B5: 3000 | C5: 3500 | D5: =B5*C5 -> 10500000 | E5: TRM asumida 3.500 - confirmar
A6: INGRAM | B6: 4876 | C6: 3500 | D6: =B6*C6 -> 17066000 | E6: TRM asumida 3.500 - confirmar
A7: Total ingreso | B7: =SUM(B5:B6) -> 7876 | D7: =SUM(D5:D6) -> 27566000
A9: 2. SALIDAS (EJECUCIÓN)
A10: Tipo | B10: Concepto | C10: Fecha / Cupos | D10: COP | E10: Observación
B11: Sin ejecuciones registradas | D11: 0
A12: Total salida | D12: =SUM(D11:D11) -> 0
A14: 3. RESUMEN
A15: Total ingreso (COP) | D15: =D7 -> 27566000
A16: Total salida (COP) | D16: =D12 -> 0
A17: SALDO (COP) | D17: =D15-D16 -> 27566000
A18: Comisión Dir. Mercadeo (10%) | D18: =D17*10% -> 2756600
A21: Notas: la hoja original solo tenía los USD sin TRM ni COP. Se aplicó TRM 3.500 (la estándar del libro) - CONFIRMAR. No hay salidas registradas, por lo que todo el fondo figura disponible.

Sheet Cisco
A1: FONDOS CISCO
A3: 1. INGRESO DE FONDOS
A4: Periodo | B4: USD | C4: TRM | D4: COP | E4: Observación
A5: Único | B5: 3000 | C5: =D5/B5 -> 3333.3333 | D5: 10000000 | E5: TRM implícita (COP/USD), distinta a 3.500 de las demás marcas
A6: Total ingreso | B6: =SUM(B5:B5) -> 3000 | D6: =SUM(D5:D5) -> 10000000
A8: 2. SALIDAS (EJECUCIÓN)
A9: Tipo | B9: Concepto | C9: Fecha / Cupos | D9: COP | E9: Observación
A10: Rio | B10: Rio (20 al 24 mayo) - cupos @ $6.500.000 | C10: 1.5 | D10: =C10*6500000 -> 9750000 | E10: Encabezado original decía 1 cupo
A11: Otro | B11: Saldo cruza negocio María Paola | D11: =D6-D10 -> 250000
A12: Total salida | D12: =SUM(D10:D11) -> 10000000
A14: 3. RESUMEN
A15: Total ingreso (COP) | D15: =D6 -> 10000000
A16: Salidas - Rio | D16: =SUMIF($A$10:$A$11,"Rio",$D$10:$D$11) -> 9750000
A17: Salidas - Otros | D17: =SUMIF($A$10:$A$11,"Otro",$D$10:$D$11) -> 250000
A18: Total salida (COP) | D18: =D12 -> 10000000
A19: SALDO (COP) | D19: =D15-D18 -> 0
A22: Notas: la TRM 3.333,33 estaba implícita (el COP era un valor fijo). Aquí queda explícita en C5. Si se usara TRM 3.500 el ingreso sería $10.500.000 (+$500.000).

Sheet Champion
A1: CHAMPION (HP + DELL)
A3: 1. INGRESO DE FONDOS
A4: Periodo | B4: USD | C4: TRM | D4: COP | E4: Observación
D5: 0 | E5: Sin ingreso de fondos registrado
A6: Total ingreso | D6: =SUM(D5:D5) -> 0
A8: 2. SALIDAS (EJECUCIÓN)
A9: Marca | B9: Periodo | C9: USD | D9: TRM | E9: COP
A10: HP | B10: Q1 | C10: 2000 | D10: 3500 | E10: =C10*D10 -> 7000000
A11: HP | B11: Q2 | C11: 2000 | D11: 3500 | E11: =C11*D11 -> 7000000
A12: DELL | B12: Q1 | C12: 2000 | D12: 3500 | E12: =C12*D12 -> 7000000
A13: DELL | B13: Q2 | C13: 2000 | D13: 3500 | E13: =C13*D13 -> 7000000
A14: Subtotal HP | C14: =SUMIF($A$10:$A$13,"HP",$C$10:$C$13) -> 4000 | E14: =SUMIF($A$10:$A$13,"HP",$E$10:$E$13) -> 14000000
A15: Subtotal DELL | C15: =SUMIF($A$10:$A$13,"DELL",$C$10:$C$13) -> 4000 | E15: =SUMIF($A$10:$A$13,"DELL",$E$10:$E$13) -> 14000000
A16: Total salida | C16: =SUM(C10:C13) -> 8000 | E16: =SUM(E10:E13) -> 28000000
A18: 3. RESUMEN
A19: Total ingreso (COP) | E19: =D6 -> 0
A20: Total salida (COP) | E20: =E16 -> 28000000
A21: SALDO (COP) | E21: =E19-E20 -> -28000000
A24: Notas: Champion registra un gasto de USD 8.000 ($28.000.000) sin ningún ingreso de fondos asociado; por eso el saldo es negativo. La TRM 3.500 estaba incrustada en la fórmula y ahora está en celdas editables (D10:D13).

Sheet Total Fondos 
G2: CONSOLIDADO DE FONDOS POR MARCA
G4: Marca | H4: Ingreso | I4: Salida | J4: Saldo | K4: % Ejecutado
G5: Hp | H5: =Hp!D14 -> 60200000 | I5: =Hp!D29 -> 45862168 | J5: =H5-I5 -> 14337832 | K5: =IF(H5=0,"",I5/H5) -> 0.76183003
G6: Dell | H6: =Dell!D11 -> 57947715 | I6: =Dell!D20 -> 33927450 | J6: =H6-I6 -> 24020265 | K6: =IF(H6=0,"",I6/H6) -> 0.58548383
G7: Lenovo | H7: =Lenovo!D8 -> 17160500 | I7: =Lenovo!D17 -> 17158950 | J7: =H7-I7 -> 1550 | K7: =IF(H7=0,"",I7/H7) -> 0.99990968
G8: Intel | H8: =Intel!D6 -> 17465000 | I8: =Intel!D13 -> 17465000 | J8: =H8-I8 -> 0 | K8: =IF(H8=0,"",I8/H8) -> 1
G9: Cisco | H9: =Cisco!D6 -> 10000000 | I9: =Cisco!D12 -> 10000000 | J9: =H9-I9 -> 0 | K9: =IF(H9=0,"",I9/H9) -> 1
G10: Microsoft | H10: =Microsoft!D7 -> 27566000 | I10: =Microsoft!D12 -> 0 | J10: =H10-I10 -> 27566000 | K10: =IF(H10=0,"",I10/H10) -> 0
G11: Champion | H11: =Champion!D6 -> 0 | I11: =Champion!E16 -> 28000000 | J11: =H11-I11 -> -28000000 | K11: =IF(H11=0,"",I11/H11)
G12: TOTAL | H12: =SUM(H5:H11) -> 190339215 | I12: =SUM(I5:I11) -> 152413568 | J12: =SUM(J5:J11) -> 37925647 | K12: =IF(H12=0,"",I12/H12) -> 0.80074707
G13: Comisión Dir. Mercadeo (10% del saldo) | H13: =J12*10% -> 3792564.7
G15: OBSERVACIONES Y AJUSTES REALIZADOS
G16: Hoja | H16: Celda | I16: Observación | J16: Impacto (COP)
G17: Todas | H17: - | I17: Se estandarizó la estructura: 1. Ingreso de fondos / 2. Salidas / 3. Resumen. Azul = dato editable, negro = fórmula. | J17: 0
G18: Microsoft | H18: D5:D6 | I18: Antes solo tenía USD sin TRM ni COP; se aplicó TRM 3.500 y ahora entra al consolidado | J18: =Microsoft!D7 -> 27566000
G19: Lenovo | H19: D8 | I19: El Q4 (sin factura Provexpress) se excluye del ingreso confirmado y se muestra aparte en D9 | J19: =Lenovo!D7 -> 11721500
G20: Champion | H20: E16 | I20: Gasto de USD 8.000 sin ingreso de fondos asociado; genera saldo negativo | J20: =-Champion!E16 -> -28000000
G21: Dell | H21: D10 | I21: El ingreso incluye 'Fondos Proposal' (USD 9.500) aún no ejecutado | J21: =Dell!D10 -> 33250000
G22: Dell | H22: E6 | I22: Vigencia Q4 dice 'enero 30' pero por secuencia debería cerrar en enero 2027 | J22: 0
G23: Intel | H23: C12 | I23: Encabezado original decía 2 cupos de Rio pero calculaba 1,5; se dejó 1,5 (editable) | J23: =6500000*2-Intel!D12 -> 3250000
G24: Cisco | H24: C10 | I24: Encabezado original decía 1 cupo de Rio pero calculaba 1,5; se dejó 1,5 (editable) | J24: =6500000*1-Cisco!D10 -> -3250000
G25: Cisco | H25: C5 | I25: TRM implícita 3.333,33 vs 3.500 usada en las demás marcas | J25: =Cisco!B5*3500-Cisco!D5 -> 500000
G26: Hp | H26: A18:D28 | I26: Los conceptos de evento/incentivo estaban corridos una columna respecto a sus montos; se realinearon | J26: 0
